main_pkg/__init__.py
main_pkg/app.py
main_pkg/io_utils.py
main_pkg/schedule.py
main_pkg/wsgi.py
scripts/__init__.py
scripts/zx_config_app.py
zx_config_manager-0.2.8.data/scripts/zx_config_app.py
zx_config_manager-0.2.8.dist-info/METADATA
zx_config_manager-0.2.8.dist-info/WHEEL
zx_config_manager-0.2.8.dist-info/entry_points.txt
zx_config_manager-0.2.8.dist-info/top_level.txt
zx_config_manager-0.2.8.dist-info/RECORD
