Metadata-Version: 2.1
Name: zx-config-manager
Version: 0.2.8
Summary: zx-config-manager is a tool for managing configuration files.
Home-page: https://gitee.com/programer/zx-config-manager.git
Author: shallots
Author-email: shallotsh@gmail.com
Classifier: Programming Language :: Python :: 3
Classifier: License :: OSI Approved :: MIT License
Classifier: Operating System :: OS Independent
Requires-Python: >=3.6
Requires-Dist: flask >=1.1.1
Requires-Dist: uwsgi >=2.0.17
Requires-Dist: APScheduler >=3.6.3
